__init__.py
demo/ctm_simulation.py
demo/demand.py
demo/metanet_simulation.py
demo/plot_network.py
demo/scenarios.py
traffic_flow_models/__init__.py
traffic_flow_models/controller/__init__.py
traffic_flow_models/controller/alinea.py
traffic_flow_models/model/__init__.py
traffic_flow_models/model/ctm.py
traffic_flow_models/model/helpers.py
traffic_flow_models/model/metanet.py
traffic_flow_models/network/__init__.py
traffic_flow_models/network/cell.py
traffic_flow_models/network/network.py
traffic_flow_models/network/offramp.py
traffic_flow_models/network/onramp.py
traffic_flow_models/simulator/__init__.py
traffic_flow_models-0.1.3.dist-info/licenses/LICENSE
traffic_flow_models-0.1.3.dist-info/METADATA
traffic_flow_models-0.1.3.dist-info/WHEEL
traffic_flow_models-0.1.3.dist-info/top_level.txt
traffic_flow_models-0.1.3.dist-info/RECORD
