Metadata-Version: 2.4
Name: traffic_flow_models
Version: 0.1.3
Summary: Traffic flow models and simulator
Author-email: Julius Schlapbach <juliussc@ethz.ch>
Requires-Python: >=3.13
License-File: LICENSE
Requires-Dist: numpy==2.3.4
Requires-Dist: scipy==1.16.3
Requires-Dist: matplotlib==3.10.7
Provides-Extra: dev
Requires-Dist: pytest==9.0.0; extra == "dev"
Requires-Dist: git-cliff==2.11.0; extra == "dev"
Dynamic: license-file
